knowknow/__init__.py
knowknow/__main__.py
knowknow/code_sharing.py
knowknow/config.yaml
knowknow/dataverse.py
knowknow/desktop.ini
knowknow/env.py
knowknow/exceptions.py
knowknow/meta_notebook.py
knowknow/nlp.py
knowknow/osf.py
knowknow/utility.py
knowknow/viz.py
knowknow/wos.backup.py
knowknow/datastore_cnts/__init__.py
knowknow/datastore_cnts/count_cache.py
knowknow/datastore_cnts/counter.py
knowknow/datastore_cnts/representations.py
knowknow/datastore_cnts/stats.py
knowknow/datastore_cnts/time_trend.py
knowknow/datastore_sql/__init__.py
knowknow/datastore_sql/count_cache.py
knowknow/datastore_sql/dbmodel.py
knowknow/datastore_sql/dbquery.py
knowknow/datastore_sql/example_usage.py
knowknow/datastore_sql/group_references.py
knowknow/datastore_sql/wos.py
tests/__init__.py
tests/test_utility.py
knowknow_amcgail-0.3.1.dist-info/LICENSE
knowknow_amcgail-0.3.1.dist-info/METADATA
knowknow_amcgail-0.3.1.dist-info/WHEEL
knowknow_amcgail-0.3.1.dist-info/top_level.txt
knowknow_amcgail-0.3.1.dist-info/RECORD
