Metadata-Version: 2.1
Name: knowknow-amcgail
Version: 0.3.1
Summary: Analyzing the evolution of ideas using citation analysis
Home-page: https://github.com/amcgail/knowknow
Author: Alec McGail
Author-email: amcgail2@gmail.com
License: UNKNOWN
Platform: UNKNOWN
Classifier: Programming Language :: Python :: 3
Classifier: License :: OSI Approved :: MIT License
Classifier: Operating System :: OS Independent
Requires-Python: >=3.6
License-File: LICENSE
Requires-Dist: colour (>=0.1.5)
Requires-Dist: cycler (>=0.10.0)
Requires-Dist: editdistance (>=0.5.3)
Requires-Dist: ipython (>=7.14.0)
Requires-Dist: jupyter (>=1.0.0)
Requires-Dist: IPython
Requires-Dist: jupyterlab (>=2.1.2)
Requires-Dist: lxml (>=4.4.1)
Requires-Dist: matplotlib (>=3.2.1)
Requires-Dist: nameparser (>=1.0.6)
Requires-Dist: networkx (>=2.3)
Requires-Dist: nltk (>=3.5)
Requires-Dist: numpy (>=1.18.4)
Requires-Dist: pandas (>=1.0.3)
Requires-Dist: PyYAML (>=5.3.1)
Requires-Dist: scikit-learn (>=0.23.0)
Requires-Dist: scipy (>=1.4.1)
Requires-Dist: seaborn (>=0.10.1)
Requires-Dist: six (>=1.14.0)
Requires-Dist: statsmodels (>=0.11.1)
Requires-Dist: string-grouper (>=0.1.0)
Requires-Dist: tabulate (>=0.8.7)
